etsformer_pytorch/__init__.py
etsformer_pytorch/etsformer_pytorch.py
ETSformer_pytorch-0.1.1.dist-info/LICENSE
ETSformer_pytorch-0.1.1.dist-info/METADATA
ETSformer_pytorch-0.1.1.dist-info/WHEEL
ETSformer_pytorch-0.1.1.dist-info/top_level.txt
ETSformer_pytorch-0.1.1.dist-info/RECORD
